{
  "users": [
    {
      "id": 1,
      "name": "Lola",
      "age": 1
    },
    {
      "name": "Pepe",
      "age": 0,
      "id": 2
    },
    {
      "name": "Pepe",
      "age": 0,
      "id": 3
    },
    {
      "name": "Pepe",
      "age": 0,
      "id": 4
    },
    {
      "name": "Anna",
      "age": 20,
      "id": 5
    },
    {
      "name": "Pepe",
      "age": 0,
      "id": 6
    },
    {
      "name": "Pepe",
      "age": 0,
      "id": 7
    },
    {
      "name": "Pepe",
      "age": 0,
      "id": 8
    },
    {
      "name": "Pepe",
      "age": 0,
      "id": 9
    },
    {
      "name": "NAME",
      "age": 25,
      "id": 10
    },
    {
      "name": "NAME",
      "age": 25,
      "id": 11
    },
    {
      "name": "dsfdsa",
      "age": 71,
      "id": 12
    }
  ]
}